dashhtmlgrid/__init__.py
dashhtmlgrid/__main__.py
dashhtmlgrid/data_table.py
dashhtmlgrid/dropdown.py
dashhtmlgrid/html_layout.py
dashhtmlgrid/plt_children.py
dashhtmlgrid/textarea_with_submit.py
dashhtmlgrid/common/visualization.py
dashhtmlgrid/tests/__init__.py
dashhtmlgrid/tests/example_data_table.py
dashhtmlgrid/tests/example_stock_data.py
dashhtmlgrid/tests/plotly_dash_dropdown_graph.py
dashhtmlgrid/tests/test_data_table_with_call_back.py
dashhtmlgrid/tests/test_htmlgrid_dropdown_multiple_options.py
dashhtmlgrid/tests/test_htmlgrid_dropdown_single_option.py
dashhtmlgrid/tests/test_htmlgrid_textarea_submit_figures.py
dashhtmlgrid/tests/test_htmlgrid_textarea_submit_table.py
dashhtmlgrid/tests/test_simple_textarea_with_echo.py
dashhtmlgrid/tests/test_textarea_with_submit.py
dashhtmlgrid/tests/test_visualizations.py
dashhtmlgrid-0.1.0.dist-info/LICENSE
dashhtmlgrid-0.1.0.dist-info/METADATA
dashhtmlgrid-0.1.0.dist-info/WHEEL
dashhtmlgrid-0.1.0.dist-info/entry_points.txt
dashhtmlgrid-0.1.0.dist-info/top_level.txt
dashhtmlgrid-0.1.0.dist-info/RECORD
